Workbook

Sheet 假設
A1: V3 補充：電池 + 充電器拆分為訂閱｜入手價、訂閱費、輪內可拆成本、護城河
A2: 藍字 = 可調輸入（取自「單速+Hub-motor 整車出廠價降本模型 V3」與 StealthWheel 盡調報告）；黑字 = 公式；綠字 = 跨表連結。2026-09-21
A4: A. V3 模型基準（中國 FOB，10 萬台/年）
A5: 參數 | B5: 值 | C5: 來源
A6: 極簡 180Wh 配置材料合計（RMB） | B6: 1121 | C6: V3 1_假設與單價 C43（鋼架/V煞/PAS/單鍵/單速/180Wh）
A7: 直接組裝工時 + QC（RMB/台） | B7: 22 | C7: V3 B8
A8: ODM 毛利率（爭取值） | B8: 0.13 | C8: V3 B9
A9: ODM 毛利率（實際可能） | B9: 0.18 | C9: V3 分頁 3：富士達電助力車事業 18.94%
A10: 電芯單價（RMB/Wh） | B10: 0.66 | C10: V3 B10
A11: 電池包固定成本（RMB） | B11: 120 | C11: V3 B11：BMS + 外殼/軌道/鎖 + 連接器/點焊/測試，不隨容量縮小
A12: 電池包加工毛利 | B12: 0.18 | C12: V3 B12
A13: 充電器 36V 2A（RMB） | B13: 40 | C13: V3 C31
A14: 日本版力矩感測淨增額（RMB 材料） | B14: 160 | C14: V3 分頁 7 D15（力矩中軸 160 − 標準中軸 7 + 線束 14 + 校正 3 − PAS 10 ≈ 160）
A15: 日本版非 BOM 增額（型式認定/PSE/說明書/OTP，RMB） | B15: 7.3 | C15: V3 分頁 7 B40:B43
A17: B. 匯率（V3 一致）
A18: 參數 | B18: 值 | C18: 來源
A19: RMB / EUR | B19: 10.8 | C19: V3 分頁 10
A20: NTD / RMB | B20: 4.54 | C20: V3 B7
A21: JPY / RMB | B21: 23.5 | C21: V3 分頁 8 B7
A23: C. 車體零售（入手價）假設
A24: 參數 | B24: 值 | C24: 來源
A25: 歐洲：關稅（台越製 MFN；中國製不適用） | B25: 0.06 | C25: V3 分頁 10 B36。注意：中國 FOB 出貨至歐盟另有 AD+CVD，本表沿用 V3 假設以台越製計
A26: 歐洲：運費（€/台） | B26: 8 | C26: V3 分頁 10
A27: 歐洲：DTC 毛利率 | B27: 0.35 | C27: V3
A28: 歐洲：經銷抽成 | B28: 0.38 | C28: V3
A29: 歐洲：VAT | B29: 0.19
A30: 台灣：DTC 毛利率 | B30: 0.35 | C30: V3
A31: 台灣：營業稅 | B31: 0.05
A32: 日本：出口報關/內陸 4% | B32: 0.04 | C32: V3 分頁 8 B9
A33: 日本：海運保險（¥/台） | B33: 1800 | C33: V3 B10
A34: 日本：通關拖運（¥/台） | B34: 800 | C34: V3 B14
A35: 日本：PSE 逐台檢查 + 認證攤提（¥/台） | B35: 600 | C35: V3 B15
A36: 日本：PDI/說明書/防犯登録/保固準備（¥/台） | B36: 3500 | C36: V3 B16
A37: 日本：通路 PB 情境 PDI 減項（¥） | B37: 3500 | C37: V3 B25
A38: 日本：通路 PB 零售毛利 | B38: 0.3 | C38: V3 E25
A39: 日本：BESV 壓縮進口毛利 | B39: 0.15 | C39: V3 C24
A40: 日本：經銷零售毛利 | B40: 0.22 | C40: V3 E24
A41: 日本：消費稅 | B41: 0.1
A43: D. 電池訂閱費：成本堆疊定價假設（三市場）
A44: 參數 | B44: 歐洲 € / 台灣 NT$ / 日本 ¥（同列三值見備註） | C44: 說明
A45: D-歐洲（EUR）
A46: VAT / 稅 | B46: 0.19 | C46: V3 分頁 10：VAT 19%、呆帳 6%、金流 2.5%、客服 €1.0、維修物流 €0.2；更換物流 €30 為 UN3480 經銷點陸運（盡調報告 €20–50）；CAC €30 為隨車成交假設
A47: 呆帳率 | B47: 0.06
A48: 金流手續費 | B48: 0.025
A49: 客服/APP/雲端（每戶/月） | B49: 1
A50: 維修與物流準備（每戶/月） | B50: 0.2
A51: 失竊補償準備（每戶/月） | B51: 0.5
A52: 電池更換週期（月） | B52: 48
A53: 更換物流（每次，經銷點） | B53: 30
A54: 訂閱壽命（月） | B54: 36
A55: CAC（隨車成交） | B55: 30
A56: 期末電池殘值率 | B56: 0.15
A57: 營運商目標貢獻率（對淨月費） | B57: 0.25
A58: 電池落地物流分攤（每顆） | B58: 4
A59: D-台灣（NT$）
A60: VAT / 稅 | B60: 0.05 | C60: 假設值；Gogoro 電池服務 NT$319–1,269/月為消費者錨點；台灣無自行車訂閱先例
A61: 呆帳率 | B61: 0.04
A62: 金流手續費 | B62: 0.02
A63: 客服/APP/雲端（每戶/月） | B63: 30
A64: 維修與物流準備（每戶/月） | B64: 8
A65: 失竊補償準備（每戶/月） | B65: 15
A66: 電池更換週期（月） | B66: 48
A67: 更換物流（每次，經銷點） | B67: 300
A68: 訂閱壽命（月） | B68: 36
A69: CAC（隨車成交） | B69: 800
A70: 期末電池殘值率 | B70: 0.15
A71: 營運商目標貢獻率（對淨月費） | B71: 0.25
A72: 電池落地物流分攤（每顆） | B72: 100
A73: D-日本（JPY）
A74: VAT / 稅 | B74: 0.1 | C74: V3 分頁 9：NORUDE 盜難補償 ¥700/月為加購；B2B2C 通路（電鐵/電力/物管）CAC 趨近零，取 ¥3,000
A75: 呆帳率 | B75: 0.03
A76: 金流手續費 | B76: 0.035
A77: 客服/APP/雲端（每戶/月） | B77: 100
A78: 維修與物流準備（每戶/月） | B78: 60
A79: 失竊補償準備（每戶/月） | B79: 80
A80: 電池更換週期（月） | B80: 48
A81: 更換物流（每次，經銷點） | B81: 3000
A82: 訂閱壽命（月） | B82: 36
A83: CAC（B2B2C 通路） | B83: 3000
A84: 期末電池殘值率 | B84: 0.15
A85: 營運商目標貢獻率（對淨月費） | B85: 0.25
A86: 電池落地物流分攤（每顆） | B86: 300
A88: E. 輪內可拆（分體花鼓母模）方案假設
A89: 參數 | B89: 值 | C89: 來源
A90: 輪內母模 180Wh 模組成本（USD，不含 PD3.1） | B90: 78 | C90: 盡調報告第四節重估 US$88 含 PD3.1 雙向 buck-boost US$10；扣除後 78（電芯 28 + BMS 8 + 鍍金冠簧/卡口/氟膠/CNC 鋁殼 42）
A91: USD / RMB | B91: 7.05 | C91: V3 B6
A92: 客製分體公模馬達（含卡口與導電環，RMB） | B92: 500 | C92: V3 分頁 6：TK-06U 級距合理估 RMB 400–600
A93: 商品化 250W 齒輪輪轂（RMB） | B93: 205 | C93: V3 C28
A94: 車架後下叉間隙特製（RMB/台） | B94: 28 | C94: 盡調報告：車架 US$58→62（+US$4）
A95: IP67 組裝、扭力管制與氣密測試增額（RMB/台） | B95: 32 | C95: 盡調報告：包裝組裝 US$9.5→14（+US$4.5）
A96: 編輪偏擺處理與檢驗增額（RMB/台） | B96: 15 | C96: 假設：兩側法蘭同在公模，輪組偏擺（盡調矛盾 4）
A97: 模具與專屬認證 NRE（USD） | B97: 250000 | C97: 假設：公母模壓鑄/CNC 模具 + 卡口/導電環驗證 + 重做 EN 15194/EN 50604 系統認證
A98: NRE 攤提量（台） | B98: 100000 | C98: 10 萬台/年 × 1 年（保守：以首年量攤提）
A99: 輪內電池因受熱之更換週期（月） | B99: 36 | C99: 盡調矛盾 3：馬達 60–90°C 傳導 + 電池 I²R；台日夏季更差。48→36
A100: 車架包電芯層級可更換設計增額（RMB/包） | B100: 20 | C100: 假設：螺絲殼體 + 電芯座/彈簧接點取代點焊鎳片；歐盟電池法 Art.11（2027/2/18）
A101: 車架包電芯級可更換之翻新成本（佔新品） | B101: 0.3 | C101: V3 分頁 5：翻新成本降至新品 20–30%

Sheet 入手價
A1: 入手價：把電池與充電器移出整車後，各市場的出廠價與零售價
A2: 單位依欄標。配置 C 為本次計算重點；A、B 為 V3 既有基準的對照。
A4: A. 材料與出廠價（RMB）
A5: 配置 | B5: 材料 RMB | C5: 出廠 @13% | D5: 出廠 @18% | E5: NT$ 出廠 @13% | F5: NT$ 出廠 @18% | I5: 說明
A6: A 極簡 180Wh 含電池含充電器（V3 基準） | B6: =假設!$B$6 -> 1121 | C6: =(B6+假設!$B$7)/(1-假設!$B$8) -> 1313.7931 | D6: =(B6+假設!$B$7)/(1-假設!$B$9) -> 1393.9024 | E6: =C6*假設!$B$20 -> 5964.6207 | F6: =D6*假設!$B$20 -> 6328.3171 | I6: V3 分頁 3 C6：RMB 1,314
A7: B 不含電池、含充電器（V3 分頁 10） | B7: =假設!$B$6-((180)*假設!$B$10+假設!$B$11)*(1+假設!$B$12) -> 839.216 | C7: =(B7+假設!$B$7)/(1-假設!$B$8) -> 989.90345 | D7: =(B7+假設!$B$7)/(1-假設!$B$9) -> 1050.2634 | E7: =C7*假設!$B$20 -> 4494.1617 | F7: =D7*假設!$B$20 -> 4768.1959 | I7: V3 分頁 10 C32：材料 839
A8: C 不含電池、不含充電器（本次） | B8: =假設!$B$6-((180)*假設!$B$10+假設!$B$11)*(1+假設!$B$12)-假設!$B$13 -> 799.216 | C8: =(B8+假設!$B$7)/(1-假設!$B$8) -> 943.92644 | D8: =(B8+假設!$B$7)/(1-假設!$B$9) -> 1001.4829 | E8: =C8*假設!$B$20 -> 4285.426 | F8: =D8*假設!$B$20 -> 4546.7325 | I8: 電池與充電器皆為訂閱資產
A9: D 日本版 C（力矩感測，電池 144Wh 訂閱） | B9: =假設!$B$6-((180)*假設!$B$10+假設!$B$11)*(1+假設!$B$12)-假設!$B$13+假設!$B$14+假設!$B$15 -> 966.516 | C9: =(B9+假設!$B$7)/(1-假設!$B$8) -> 1136.2253 | D9: =(B9+假設!$B$7)/(1-假設!$B$9) -> 1205.5073 | E9: =C9*假設!$B$20 -> 5158.4628 | F9: =D9*假設!$B$20 -> 5473.0032 | I9: V3 分頁 7：力矩 +160、非 BOM +7.3；電池降配 144Wh 在訂閱側
A10: C 對 A 的出廠價降幅 | C10: =1-C8/C6 -> 0.28152581 | I10: 電池 + 充電器移出後，車體出廠價降 28%
A11: 訂閱資產：180Wh 電池 + 充電器（RMB） | B11: =((180)*假設!$B$10+假設!$B$11)*(1+假設!$B$12)+假設!$B$13 -> 321.784 | I11: 電池 282 + 充電器 40
A13: B. 歐洲與台灣零售（配置 C）
A14: 項目 | B14: 歐洲 € | C14: 台灣 NT$ | I14: 公式 / 對照
A15: 出廠價（配置 C，ODM 13%） | B15: =C8/假設!$B$19 -> 87.400596 | C15: =E8 -> 4285.426 | I15: RMB ÷ 10.8；NT$ 直接取
A16: 落地成本（歐洲：關稅 6% + €8；台灣：假設 +NT$150 運費） | B16: =B15*(1+假設!$B$25)+假設!$B$26 -> 100.64463 | C16: =C15+150 -> 4435.426 | I16: V3 分頁 10 D36 結構
A17: DTC 零售（含稅） | B17: =B16/(1-假設!$B$27)*(1+假設!$B$46) -> 184.2571 | C17: =C16/(1-假設!$B$30)*(1+假設!$B$31) -> 7164.919 | I17: ＝ 落地 ÷ (1 − 35%) × (1 + 稅)
A18: 經銷零售（含稅，歐洲抽 38%） | B18: =B16/(1-假設!$B$27)/(1-假設!$B$28)*(1+假設!$B$46) -> 297.18886 | C18: =C16/(1-假設!$B$30)/(1-0.30)*(1+假設!$B$31) -> 10235.599 | I18: 台灣經銷以抽 30% 假設
A19: 對照：市場最低價合法 e-bike 買斷 | B19: 699 | C19: 15000 | I19: 歐洲 Action E200 / Lidl €699；台灣入門電輔車約 NT$15,000（假設，內需無公開統計）
A20: 對照：一般（非電動）自行車均價 | B20: 500 | C20: 5500 | I20: 德國 ZIV 2025 €500；台灣通勤/淑女車 NT$4,000–7,000（V3 分頁 10）
A21: DTC 入手價 vs 最低價 e-bike | B21: =B17/B19-1 -> -0.73639901 | C21: =C17/C19-1 -> -0.52233874 | I21: 負值 = 入手價低於對照
A22: DTC 入手價 vs 一般自行車 | B22: =B17/B20-1 -> -0.63148581 | C22: =C17/C20-1 -> 0.30271254 | I22: V3「反向滲透」檢核：歐洲成立、台灣勉強
A24: C. 日本零售（配置 D，V3 分頁 8 結構）
A25: 項目 | B25: ¥/台 | I25: 說明
A26: 出廠價（配置 D，ODM 13%，RMB） | B26: =C9 -> 1136.2253
A27: 出廠價（¥） | B27: =B26*假設!$B$21 -> 26701.294
A28: CIF（+4% 報關 + 海運保險） | B28: =B27*(1+假設!$B$32)+假設!$B$33 -> 29569.346
A29: 進口商全載成本（+通關 + PSE + PDI；關稅 0%） | B29: =B28+假設!$B$34+假設!$B$35+假設!$B$36 -> 34469.346 | I29: V3：HS 8711.60 無稅；消費稅可扣抵不計
A30: 情境 3：通路自有品牌 PB 零售（税込） | B30: =(B29-假設!$B$37)/(1-假設!$B$38)*(1+假設!$B$41) -> 48666.115 | I30: V3 情境 3 已用 Cainz ¥59,800 / ドンキ ¥65,780 校準
A31: 情境 2：BESV 壓縮毛利 15% + 經銷 22%（税込） | B31: =B29/(1-假設!$B$39)/(1-假設!$B$40)*(1+假設!$B$41) -> 57188.96
A32: 對照：Cainz PB ¥59,800／Panasonic ビビ EYX ¥89,800／NORUDE ¥2,890×36 | B32: 59800 | I32: V3 分頁 8 C 段
A33: PB 入手價 vs Cainz | B33: =B30/B32-1 -> -0.18618536 | I33: 電池不在車價內，PB 通路入手價可低於現有最低價帶

Sheet 電池訂閱費
A1: 電池訂閱費：成本堆疊定價（三市場 × 三容量）
A2: 建議月費 = [資產攤提 + 更換準備 + 失竊 + 客服 + 維修物流 + CAC 攤提] ÷ (1 − 目標貢獻率) ÷ (1 − 呆帳 − 金流) × (1 + 稅)。再以「建議定價（取整）」回算貢獻與淨值。
A4: 歐洲 €（每戶每月）
A5: 項目 | B5: 180 Wh | C5: 250 Wh | D5: 360 Wh | K5: 公式 / 說明
A6: 電池包 FOB（RMB） | B6: =((180)*假設!$B$10+假設!$B$11)*(1+假設!$B$12) -> 281.784 | C6: =((250)*假設!$B$10+假設!$B$11)*(1+假設!$B$12) -> 336.3 | D6: =((360)*假設!$B$10+假設!$B$11)*(1+假設!$B$12) -> 421.968 | K6: V3 成本函數 (Wh×0.66+120)×1.18
A7: 電池落地成本（當地幣） | B7: =B6/假設!$B$19*(1+假設!$B$25)+假設!$B$58 -> 31.656578 | C7: =C6/假設!$B$19*(1+假設!$B$25)+假設!$B$58 -> 37.007222 | D7: =D6/假設!$B$19*(1+假設!$B$25)+假設!$B$58 -> 45.415378 | K7: RMB / 10.8 × 1.06 + 物流分攤
A8: 充電器落地成本（當地幣） | B8: =假設!$B$13/假設!$B$19*(1+假設!$B$25) -> 3.9259259 | C8: =假設!$B$13/假設!$B$19*(1+假設!$B$25) -> 3.9259259 | D8: =假設!$B$13/假設!$B$19*(1+假設!$B$25) -> 3.9259259 | K8: 日本充電器為 ◇PSE 特定電気用品，認證費另計
A9: 每戶訂閱資產（電池 + 充電器） | B9: =B7+B8 -> 35.582504 | C9: =C7+C8 -> 40.933148 | D9: =D7+D8 -> 49.341304 | K9: 對照 V3 分頁 10：三電訂閱資產 €69、電池 €32
A10: ① 電池資產攤提 = 資產 × (1 − 殘值) ÷ 壽命 | B10: =B7*(1-假設!$B$56)/假設!$B$54 -> 0.74744698 | C10: =C7*(1-假設!$B$56)/假設!$B$54 -> 0.87378164 | D10: =D7*(1-假設!$B$56)/假設!$B$54 -> 1.0723075
A11: ② 充電器攤提 = 充電器 ÷ 壽命 | B11: =B8/假設!$B$54 -> 0.1090535 | C11: =C8/假設!$B$54 -> 0.1090535 | D11: =D8/假設!$B$54 -> 0.1090535
A12: ③ 電池更換準備 = (電池 + 更換物流) ÷ 更換週期 | B12: =(B7+假設!$B$53)/假設!$B$52 -> 1.284512 | C12: =(C7+假設!$B$53)/假設!$B$52 -> 1.3959838 | D12: =(D7+假設!$B$53)/假設!$B$52 -> 1.5711537 | K12: SoH < 70% 免費換新的準備金；物流走經銷點（UN3480）
A13: ④ 失竊補償 + ⑤ 客服/雲端 + ⑥ 維修物流 | B13: =假設!$B$51+假設!$B$49+假設!$B$50 -> 1.7 | C13: =假設!$B$51+假設!$B$49+假設!$B$50 -> 1.7 | D13: =假設!$B$51+假設!$B$49+假設!$B$50 -> 1.7 | K13: 按戶固定，不隨電池大小縮小（V3 分頁 9/10 的核心結構）
A14: ⑦ CAC 攤提 = CAC ÷ 壽命 | B14: =假設!$B$55/假設!$B$54 -> 0.83333333 | C14: =假設!$B$55/假設!$B$54 -> 0.83333333 | D14: =假設!$B$55/假設!$B$54 -> 0.83333333
A15: 每戶每月成本合計 | B15: =SUM(B10:B14) -> 4.6743458 | C15: =SUM(C10:C14) -> 4.9121523 | D15: =SUM(D10:D14) -> 5.2858481
A16: 所需淨月費 = 成本 ÷ (1 − 目標貢獻率) | B16: =B15/(1-假設!$B$57) -> 6.2324611 | C16: =C15/(1-假設!$B$57) -> 6.5495364 | D16: =D15/(1-假設!$B$57) -> 7.0477974
A17: 建議月費（含稅、含呆帳金流）= 淨月費 ÷ (1 − 呆帳 − 金流) × (1 + 稅) | B17: =B16/(1-假設!$B$47-假設!$B$48)*(1+假設!$B$46) -> 8.1056052 | C17: =C16/(1-假設!$B$47-假設!$B$48)*(1+假設!$B$46) -> 8.5179762 | D17: =D16/(1-假設!$B$47-假設!$B$48)*(1+假設!$B$46) -> 9.1659879 | K17: 成本堆疊得出的月費
A18: 損益兩平月費（貢獻率 0） | B18: =B15/(1-假設!$B$47-假設!$B$48)*(1+假設!$B$46) -> 6.0792039 | C18: =C15/(1-假設!$B$47-假設!$B$48)*(1+假設!$B$46) -> 6.3884822 | D18: =D15/(1-假設!$B$47-假設!$B$48)*(1+假設!$B$46) -> 6.8744909
A19: 建議定價（取整，可改） | B19: 7.9 | C19: 9.9 | D19: 12.9 | K19: 對照錨點：歐洲替換電池零售 €120–180；台灣 Gogoro NT$319 起；日本 NORUDE 盜難補償 ¥700/月
A20: 以定價回算：每戶月貢獻 | B20: =B19/(1+假設!$B$46)*(1-假設!$B$47-假設!$B$48)-B15+B10+B14 -> 2.9808042 | C20: =C19/(1+假設!$B$46)*(1-假設!$B$47-假設!$B$48)-C15+C10+C14 -> 4.4071476 | D20: =D19/(1+假設!$B$46)*(1-假設!$B$47-假設!$B$48)-D15+D10+D14 -> 6.5387004 | K20: ＝ 淨收 − 現金成本（③④⑤⑥；資產與 CAC 另列）
A21: 資產回收期（月） | B21: =IF(B20>0,B9/B20,999) -> 11.937216 | C21: =IF(C20>0,C9/C20,999) -> 9.2879005 | D21: =IF(D20>0,D9/D20,999) -> 7.5460414
A22: 36 月單戶淨值 = 貢獻 × 壽命 + 殘值 − 資產 − CAC | B22: =B20*假設!$B$54+B7*假設!$B$56-B9-假設!$B$55 -> 46.474935 | C22: =C20*假設!$B$54+C7*假設!$B$56-C9-假設!$B$55 -> 93.275248 | D22: =D20*假設!$B$54+D7*假設!$B$56-D9-假設!$B$55 -> 162.86422
A23: 定價 × 36 月合計（消費者視角） | B23: =B19*36 -> 284.4 | C23: =C19*36 -> 356.4 | D23: =D19*36 -> 464.4 | K23: 對照：買斷方案第 4 年換電池 €250 / NT$6,000 / ¥35,000
A25: 台灣 NT$（每戶每月）
A26: 項目 | B26: 180 Wh | C26: 250 Wh | D26: 360 Wh | K26: 公式 / 說明
A27: 電池包 FOB（RMB） | B27: =((180)*假設!$B$10+假設!$B$11)*(1+假設!$B$12) -> 281.784 | C27: =((250)*假設!$B$10+假設!$B$11)*(1+假設!$B$12) -> 336.3 | D27: =((360)*假設!$B$10+假設!$B$11)*(1+假設!$B$12) -> 421.968 | K27: V3 成本函數 (Wh×0.66+120)×1.18
A28: 電池落地成本（當地幣） | B28: =B27*假設!$B$20+假設!$B$72 -> 1379.2994 | C28: =C27*假設!$B$20+假設!$B$72 -> 1626.802 | D28: =D27*假設!$B$20+假設!$B$72 -> 2015.7347 | K28: RMB × 4.54 + 物流分攤
A29: 充電器落地成本（當地幣） | B29: =假設!$B$13*假設!$B$20 -> 181.6 | C29: =假設!$B$13*假設!$B$20 -> 181.6 | D29: =假設!$B$13*假設!$B$20 -> 181.6 | K29: 日本充電器為 ◇PSE 特定電気用品，認證費另計
A30: 每戶訂閱資產（電池 + 充電器） | B30: =B28+B29 -> 1560.8994 | C30: =C28+C29 -> 1808.402 | D30: =D28+D29 -> 2197.3347 | K30: 對照 V3 分頁 10：三電訂閱資產 €69、電池 €32
A31: ① 電池資產攤提 = 資產 × (1 − 殘值) ÷ 壽命 | B31: =B28*(1-假設!$B$70)/假設!$B$68 -> 32.56679 | C31: =C28*(1-假設!$B$70)/假設!$B$68 -> 38.410603 | D31: =D28*(1-假設!$B$70)/假設!$B$68 -> 47.593736
A32: ② 充電器攤提 = 充電器 ÷ 壽命 | B32: =B29/假設!$B$68 -> 5.0444444 | C32: =C29/假設!$B$68 -> 5.0444444 | D32: =D29/假設!$B$68 -> 5.0444444
A33: ③ 電池更換準備 = (電池 + 更換物流) ÷ 更換週期 | B33: =(B28+假設!$B$67)/假設!$B$66 -> 34.985403 | C33: =(C28+假設!$B$67)/假設!$B$66 -> 40.141708 | D33: =(D28+假設!$B$67)/假設!$B$66 -> 48.244473 | K33: SoH < 70% 免費換新的準備金；物流走經銷點（UN3480）
A34: ④ 失竊補償 + ⑤ 客服/雲端 + ⑥ 維修物流 | B34: =假設!$B$65+假設!$B$63+假設!$B$64 -> 53 | C34: =假設!$B$65+假設!$B$63+假設!$B$64 -> 53 | D34: =假設!$B$65+假設!$B$63+假設!$B$64 -> 53 | K34: 按戶固定，不隨電池大小縮小（V3 分頁 9/10 的核心結構）
A35: ⑦ CAC 攤提 = CAC ÷ 壽命 | B35: =假設!$B$69/假設!$B$68 -> 22.222222 | C35: =假設!$B$69/假設!$B$68 -> 22.222222 | D35: =假設!$B$69/假設!$B$68 -> 22.222222
A36: 每戶每月成本合計 | B36: =SUM(B31:B35) -> 147.81886 | C36: =SUM(C31:C35) -> 158.81898 | D36: =SUM(D31:D35) -> 176.10488
A37: 所需淨月費 = 成本 ÷ (1 − 目標貢獻率) | B37: =B36/(1-假設!$B$71) -> 197.09181 | C37: =C36/(1-假設!$B$71) -> 211.75864 | D37: =D36/(1-假設!$B$71) -> 234.8065
A38: 建議月費（含稅、含呆帳金流）= 淨月費 ÷ (1 − 呆帳 − 金流) × (1 + 稅) | B38: =B37/(1-假設!$B$61-假設!$B$62)*(1+假設!$B$60) -> 220.15575 | C38: =C37/(1-假設!$B$61-假設!$B$62)*(1+假設!$B$60) -> 236.5389 | D38: =D37/(1-假設!$B$61-假設!$B$62)*(1+假設!$B$60) -> 262.28386 | K38: 成本堆疊得出的月費
A39: 損益兩平月費（貢獻率 0） | B39: =B36/(1-假設!$B$61-假設!$B$62)*(1+假設!$B$60) -> 165.11681 | C39: =C36/(1-假設!$B$61-假設!$B$62)*(1+假設!$B$60) -> 177.40418 | D39: =D36/(1-假設!$B$61-假設!$B$62)*(1+假設!$B$60) -> 196.71289
A40: 建議定價（取整，可改） | B40: 249 | C40: 299 | D40: 399 | K40: 對照錨點：歐洲替換電池零售 €120–180；台灣 Gogoro NT$319 起；日本 NORUDE 盜難補償 ¥700/月
A41: 以定價回算：每戶月貢獻 | B41: =B40/(1+假設!$B$60)*(1-假設!$B$61-假設!$B$62)-B36+B31+B35 -> 129.88444 | C41: =C40/(1+假設!$B$60)*(1-假設!$B$61-假設!$B$62)-C36+C31+C35 -> 169.49004 | D41: =D40/(1+假設!$B$60)*(1-假設!$B$61-假設!$B$62)-D36+D31+D35 -> 250.91108 | K41: ＝ 淨收 − 現金成本（③④⑤⑥；資產與 CAC 另列）
A42: 資產回收期（月） | B42: =IF(B41>0,B30/B41,999) -> 12.017601 | C42: =IF(C41>0,C30/C41,999) -> 10.669665 | D42: =IF(D41>0,D30/D41,999) -> 8.7574239
A43: 36 月單戶淨值 = 貢獻 × 壽命 + 殘值 − 資產 − CAC | B43: =B41*假設!$B$68+B28*假設!$B$70-B30-假設!$B$69 -> 2521.8353 | C43: =C41*假設!$B$68+C28*假設!$B$70-C30-假設!$B$69 -> 3737.2597 | D43: =D41*假設!$B$68+D28*假設!$B$70-D30-假設!$B$69 -> 6337.8244
A44: 定價 × 36 月合計（消費者視角） | B44: =B40*36 -> 8964 | C44: =C40*36 -> 10764 | D44: =D40*36 -> 14364 | K44: 對照：買斷方案第 4 年換電池 €250 / NT$6,000 / ¥35,000
A46: 日本 ¥（每戶每月）
A47: 項目 | B47: 144 Wh | C47: 202 Wh | D47: 360 Wh | K47: 公式 / 說明
A48: 電池包 FOB（RMB） | B48: =((144)*假設!$B$10+假設!$B$11)*(1+假設!$B$12) -> 253.7472 | C48: =((202)*假設!$B$10+假設!$B$11)*(1+假設!$B$12) -> 298.9176 | D48: =((360)*假設!$B$10+假設!$B$11)*(1+假設!$B$12) -> 421.968 | K48: V3 成本函數 (Wh×0.66+120)×1.18
A49: 電池落地成本（當地幣） | B49: =B48*假設!$B$21*(1+假設!$B$32)+假設!$B$86 -> 6501.5816 | C49: =C48*假設!$B$21*(1+假設!$B$32)+假設!$B$86 -> 7605.5461 | D49: =D48*假設!$B$21*(1+假設!$B$32)+假設!$B$86 -> 10612.898 | K49: RMB × 23.5 × 1.04 + 物流分攤
A50: 充電器落地成本（當地幣） | B50: =假設!$B$13*假設!$B$21*(1+假設!$B$32) -> 977.6 | C50: =假設!$B$13*假設!$B$21*(1+假設!$B$32) -> 977.6 | D50: =假設!$B$13*假設!$B$21*(1+假設!$B$32) -> 977.6 | K50: 日本充電器為 ◇PSE 特定電気用品，認證費另計
A51: 每戶訂閱資產（電池 + 充電器） | B51: =B49+B50 -> 7479.1816 | C51: =C49+C50 -> 8583.1461 | D51: =D49+D50 -> 11590.498 | K51: 對照 V3 分頁 10：三電訂閱資產 €69、電池 €32
A52: ① 電池資產攤提 = 資產 × (1 − 殘值) ÷ 壽命 | B52: =B49*(1-假設!$B$84)/假設!$B$82 -> 153.50956 | C52: =C49*(1-假設!$B$84)/假設!$B$82 -> 179.5754 | D52: =D49*(1-假設!$B$84)/假設!$B$82 -> 250.58231
A53: ② 充電器攤提 = 充電器 ÷ 壽命 | B53: =B50/假設!$B$82 -> 27.155556 | C53: =C50/假設!$B$82 -> 27.155556 | D53: =D50/假設!$B$82 -> 27.155556
A54: ③ 電池更換準備 = (電池 + 更換物流) ÷ 更換週期 | B54: =(B49+假設!$B$81)/假設!$B$80 -> 197.94962 | C54: =(C49+假設!$B$81)/假設!$B$80 -> 220.94888 | D54: =(D49+假設!$B$81)/假設!$B$80 -> 283.60204 | K54: SoH < 70% 免費換新的準備金；物流走經銷點（UN3480）
A55: ④ 失竊補償 + ⑤ 客服/雲端 + ⑥ 維修物流 | B55: =假設!$B$79+假設!$B$77+假設!$B$78 -> 240 | C55: =假設!$B$79+假設!$B$77+假設!$B$78 -> 240 | D55: =假設!$B$79+假設!$B$77+假設!$B$78 -> 240 | K55: 按戶固定，不隨電池大小縮小（V3 分頁 9/10 的核心結構）
A56: ⑦ CAC 攤提 = CAC ÷ 壽命 | B56: =假設!$B$83/假設!$B$82 -> 83.333333 | C56: =假設!$B$83/假設!$B$82 -> 83.333333 | D56: =假設!$B$83/假設!$B$82 -> 83.333333
A57: 每戶每月成本合計 | B57: =SUM(B52:B56) -> 701.94807 | C57: =SUM(C52:C56) -> 751.01316 | D57: =SUM(D52:D56) -> 884.67324
A58: 所需淨月費 = 成本 ÷ (1 − 目標貢獻率) | B58: =B57/(1-假設!$B$85) -> 935.93076 | C58: =C57/(1-假設!$B$85) -> 1001.3509 | D58: =D57/(1-假設!$B$85) -> 1179.5643
A59: 建議月費（含稅、含呆帳金流）= 淨月費 ÷ (1 − 呆帳 − 金流) × (1 + 稅) | B59: =B58/(1-假設!$B$75-假設!$B$76)*(1+假設!$B$74) -> 1101.095 | C59: =C58/(1-假設!$B$75-假設!$B$76)*(1+假設!$B$74) -> 1178.0599 | D59: =D58/(1-假設!$B$75-假設!$B$76)*(1+假設!$B$74) -> 1387.7227 | K59: 成本堆疊得出的月費
A60: 損益兩平月費（貢獻率 0） | B60: =B57/(1-假設!$B$75-假設!$B$76)*(1+假設!$B$74) -> 825.82126 | C60: =C57/(1-假設!$B$75-假設!$B$76)*(1+假設!$B$74) -> 883.5449 | D60: =D57/(1-假設!$B$75-假設!$B$76)*(1+假設!$B$74) -> 1040.792
A61: 建議定價（取整，可改） | B61: 980 | C61: 1280 | D61: 1680 | K61: 對照錨點：歐洲替換電池零售 €120–180；台灣 Gogoro NT$319 起；日本 NORUDE 盜難補償 ¥700/月
A62: 以定價回算：每戶月貢獻 | B62: =B61/(1+假設!$B$74)*(1-假設!$B$75-假設!$B$76)-B57+B52+B56 -> 367.89483 | C62: =C61/(1+假設!$B$74)*(1-假設!$B$75-假設!$B$76)-C57+C52+C56 -> 599.89557 | D62: =D61/(1+假設!$B$74)*(1-假設!$B$75-假設!$B$76)-D57+D52+D56 -> 877.2424 | K62: ＝ 淨收 − 現金成本（③④⑤⑥；資產與 CAC 另列）
A63: 資產回收期（月） | B63: =IF(B62>0,B51/B62,999) -> 20.329673 | C63: =IF(C62>0,C51/C62,999) -> 14.307734 | D63: =IF(D62>0,D51/D62,999) -> 13.212423
A64: 36 月單戶淨值 = 貢獻 × 壽命 + 殘值 − 資產 − CAC | B64: =B62*假設!$B$82+B49*假設!$B$84-B51-假設!$B$83 -> 3740.2695 | C64: =C62*假設!$B$82+C49*假設!$B$84-C51-假設!$B$83 -> 11153.926 | D64: =D62*假設!$B$82+D49*假設!$B$84-D51-假設!$B$83 -> 18582.163
A65: 定價 × 36 月合計（消費者視角） | B65: =B61*36 -> 35280 | C65: =C61*36 -> 46080 | D65: =D61*36 -> 60480 | K65: 對照：買斷方案第 4 年換電池 €250 / NT$6,000 / ¥35,000

Sheet 輪內可拆vs車架可拆
A1: 電池可拆卸的位置：車架可拆包（標準品）vs 輪內分體母模（StealthWheel）
A2: RMB/台。車架可拆包是 V3 電池成本函數的基準（固定成本 120 已含外殼/軌道/鎖），增量為零；輪內方案的增量取自盡調報告重估與 V3 分頁 6。
A4: 項目 | B4: 車架可拆包 | C4: 輪內分體母模 | D4: 差額 | E4: 依據
A5: 電池模組 180Wh（訂閱資產） | B5: =((180)*假設!$B$10+假設!$B$11)*(1+假設!$B$12) -> 281.784 | C5: =假設!$B$90*假設!$B$91 -> 549.9 | D5: =C5-B5 -> 268.116 | E5: 盡調：母模需鍍金同心環 + 冠簧 + 卡口 + 氟膠 O 環 + CNC 鋁殼；US$78 vs 標準包 RMB 282
A6: 馬達 | B6: =假設!$B$93 -> 205 | C6: =假設!$B$92 -> 500 | D6: =C6-B6 -> 295 | E6: 商品化輪轂無卡口/導電介面；分體公模須客製，落入 TK-06U 級距價位
A7: 車架後下叉間隙 | B7: 0 | C7: =假設!$B$94 -> 28 | D7: =C7-B7 -> 28 | E7: Ø130mm 母模須特製後下叉，失去「公版車架」優勢
A8: 組裝、IP67 氣密測試 | B8: 0 | C8: =假設!$B$95 -> 32 | D8: =C8-B8 -> 32 | E8: 扭力管制 + 氣密測試，非隨插即裝
A9: 編輪偏擺處理 | B9: 0 | C9: =假設!$B$96 -> 15 | D9: =C9-B9 -> 15 | E9: 兩側法蘭同在公模 → 輪組偏擺（dish）
A10: 模具與專屬認證 NRE 攤提 | B10: 0 | C10: =假設!$B$97*假設!$B$91/假設!$B$98 -> 17.625 | D10: =C10-B10 -> 17.625 | E10: US$250k ÷ 攤提量
A11: 增量合計（RMB/台） | B11: =SUM(B5:B10) -> 486.784 | C11: =SUM(C5:C10) -> 1142.525 | D11: =SUM(D5:D10) -> 655.741
A12: 其中落在車體（出廠價）的增量 | B12: 0 | C12: =SUM(D6:D10) -> 387.625 | D12: =C12-B12 -> 387.625 | E12: 馬達 + 車架 + 組裝 + 編輪 + NRE
A13: 其中落在訂閱資產（電池模組）的增量 | B13: 0 | C13: =D5 -> 268.116 | D13: =C13-B13 -> 268.116
A15: B. 對出廠價與訂閱費的影響（歐洲 180Wh）
A16: 指標 | B16: 車架可拆包 | C16: 輪內分體母模 | D16: 差額 | E16: 說明
A17: 車體出廠價 RMB（配置 C，ODM 13%） | B17: =入手價!C8 -> 943.92644 | C17: =(入手價!B8+C12-假設!$B$95+假設!$B$7+假設!$B$95)/(1-假設!$B$8) -> 1389.4724 | D17: =C17/B17-1 -> 0.47201345 | E17: 組裝增額計入工時；其餘計入材料
A18: 車體出廠價 NT$ | B18: =B17*假設!$B$20 -> 4285.426 | C18: =C17*假設!$B$20 -> 6308.2048 | D18: =C18-B18 -> 2022.7787 | E18: 對 NT$6,000 目標
A19: 每戶訂閱資產 €（電池 + 充電器） | B19: =電池訂閱費!B9 -> 35.582504 | C19: =C5/假設!$B$19*(1+假設!$B$25)+假設!$B$58+假設!$B$13/假設!$B$19*(1+假設!$B$25) -> 61.897593 | D19: =C19-B19 -> 26.315089
A20: 電池更換週期（月） | B20: =假設!$B$52 -> 48 | C20: =假設!$B$99 -> 36 | D20: =C20-B20 -> -12 | E20: 輪內受熱：盡調矛盾 3
A21: 成本堆疊所需月費 €（含稅） | B21: =((B19-假設!$B$13/假設!$B$19*(1+假設!$B$25))*(1-假設!$B$56)/假設!$B$54+假設!$B$13/假設!$B$19*(1+假設!$B$25)/假設!$B$54+((B19-假設!$B$13/假設!$B$19*(1+假設!$B$25))+假設!$B$53)/B20+假設!$B$51+假設!$B$49+假設!$B$50+假設!$B$55/假設!$B$54)/(1-假設!$B$57)/(1-假設!$B$47-假設!$B$48)*(1+假設!$B$46) -> 8.1056052 | C21: =((C19-假設!$B$13/假設!$B$19*(1+假設!$B$25))*(1-假設!$B$56)/假設!$B$54+假設!$B$13/假設!$B$19*(1+假設!$B$25)/假設!$B$54+((C19-假設!$B$13/假設!$B$19*(1+假設!$B$25))+假設!$B$53)/C20+假設!$B$51+假設!$B$49+假設!$B$50+假設!$B$55/假設!$B$54)/(1-假設!$B$57)/(1-假設!$B$47-假設!$B$48)*(1+假設!$B$46) -> 11.193057 | D21: =C21/B21-1 -> 0.38090332 | E21: 同一套定價公式（見電池訂閱費表）
A23: C. 車架包做到「電芯層級可更換」的成本與效益
A24: 項目 | B24: 點焊鎳片（現行） | C24: 電芯座/螺絲殼（Art.11） | D24: 差額 | E24: 說明
A25: 電池包 FOB RMB（180Wh） | B25: =((180)*假設!$B$10+假設!$B$11)*(1+假設!$B$12) -> 281.784 | C25: =((180)*假設!$B$10+假設!$B$11)*(1+假設!$B$12)+假設!$B$100 -> 301.784 | D25: =C25-B25 -> 20 | E25: +RMB 20：電芯座、彈簧接點、可拆殼體；體積能量密度約 −10%
A26: 翻新成本（佔新品） | B26: 0.6 | C26: =假設!$B$101 -> 0.3 | D26: =C26-B26 -> -0.3 | E26: 點焊包只能整包報廢或拆解回收；電芯座包可只換衰退電芯
A27: 每次翻新成本 RMB | B27: =B25*B26 -> 169.0704 | C27: =C25*C26 -> 90.5352 | D27: =C27-B27 -> -78.5352 | E27: 一次翻新即回收設計增額的 4 倍以上
A28: 法規 | B28: 2027/2/18 起不符 Art.11 | C28: 符合 | E28: 執委會指引 C/2025/214：LMT 電池可拆換義務適用於電芯層級

Sheet 護城河
A1: 護城河評估：電池 + 充電器訂閱能築起什麼
A2: 量化項目連動 V3 分頁 4/5 與本表；質性判定為分析意見。
A4: 候選護城河 | B4: 機制 | C4: 量化效益（RMB/台 或 說明） | D4: 對手複製難度 | E4: 判定
A5: 1. 依實測 duty cycle 配電池 | B5: 持有資產且看得到里程 → 70/22/8 分群配 180/250/360Wh，車隊平均 210Wh；賣斷制必須一律配 360Wh | C5: =(360*假設!$B$10+假設!$B$11)*(1+假設!$B$12)-(0.7*((180)*假設!$B$10+假設!$B$11)*(1+假設!$B$12)+0.22*((250)*假設!$B$10+假設!$B$11)*(1+假設!$B$12)+0.08*((360)*假設!$B$10+假設!$B$11)*(1+假設!$B$12)) -> 116.97576 | D5: 不持有資產者無法做；需 500–1,000 台種子車隊實測 | E5: 中強：成本護城河
A6: 2. 二次電芯降階 | B6: 回收包電芯（SoH 80%）降階給低里程用戶；賣斷制在保固與消保法上不可能 | C6: =0.3*(1-0.4)*180*假設!$B$10 -> 21.384 | D6: 同上；且需電芯級可更換的包設計（本表 C 段） | E6: 中：與 1 合計約出廠價 11%（V3）
A7: 3. 法規鎖定 | B7: EN 15194 §4.2.17.2(c) closed set of components：只有已發布的電池可運作；電池法 Art.60–62 回收義務與 Art.11 電芯可換、2027 電池護照——義務變收費項目 | C7: 第三方電池無法合法相容；護照資料（SoH 歷程）由營運商持有 → 殘值定價 | D7: 對手可自建，但需 2027 前完成合規架構；先行者取得 2 年窗口 | E7: 中：合規即鎖定
A8: 4. 電池池與翻新迴圈 | B8: 同一顆電池跨用戶流轉（升降級、二次利用、翻新 20–30%）；規模越大翻新中心利用率越高、更換預測越準 | C8: =B13 -> 47.8122 | D8: 需逆物流網（經銷點/回收點）+ 翻新產能；Gogoro 靠換電站築牆，本案靠電池池 | E8: 中：規模型
A9: 5. 通路與資產融資 | B9: B2B2C 通路（電鐵/電力/物管/JobRad）CAC 趨近零；SPV 或 JAIC 式夥伴持有電池資產 | C9: CAC €120 → €30：36 月單戶淨值 +€90（V3 分頁 9 對照） | D9: 可抄，但關係型資產需時間 | E9: 弱—中
A10: 6. 用戶轉換成本 | B10: 無電池的車是 22kg 單速車、騎不動；但這是資產與付款關係，不是數據（V3 分頁 5）；且須提供買斷電池選項與「回家模式」 | C10: 中度鎖定，同時是客訴來源 | D10: — | E10: 中，但雙面刃
A11: 7. 手感繼承／APP | B11: 4–8 個助力參數，對手 2–3 趟收斂；歐盟資料法 2023/2854 要求資料可攜 | C11: 0 | D11: 一週內 | E11: 不是護城河（V3 結論四）
A12: 8. 硬體與低價本身 | B12: V3 八項降本槓桿中七項任何中國廠一週可複製；雅迪已把電池與充電器列為獨立營收（RMB 47.3 億） | C12: 0 | D12: 即時 | E12: 不是護城河
A13: 翻新迴圈每台年化節省（RMB） | B13: =(輪內可拆vs車架可拆!B25-輪內可拆vs車架可拆!C25*假設!$B$101)/4 -> 47.8122 | C13: ＝ (新包成本 − 翻新成本) ÷ 4 年更換週期
A15: 合計：可量化的結構性成本優勢（RMB/台）
A16: 1 + 2 + 翻新迴圈 | B16: =C5+C6+B13 -> 186.17196 | C16: =B16/入手價!C6 -> 0.14170569 | D16: 佔 V3 基準出廠價 RMB 1,314 的比例
A17: 可拿來做什麼 | B17: 補回力矩感測（RMB 160）或電池容量，做出同價位對手做不到的產品；或降 €1/月訂閱費擴大滲透

Sheet 日本付款路徑
A1: 日本三條付款路徑：通路零利率分期／法人租賃 B2B2C／ふるさと納税
A2: 日本沒有德國 JobRad 型薪資扣抵制度；公司貸與自行車屬現物給與、全額課稅。本表以配置 D（力矩版）PB 通路零售價與 202Wh 電池訂閱為基準。JPY。
A4: A. 假設（藍字可改）
A5: 參數 | B5: 值 | F5: 來源 / 說明
A6: 車體零售價（平地版，PB 通路，税込） | B6: =入手價!B30 -> 48666.115 | F6: 入手價表情境 3
A7: 車體零售價（坡地／載童版，税込，估） | B7: 58000 | F7: 前次分析：扭力 + 20 吋 + 45 N·m 馬達 + 後碟 + 子乗せ車架，PB 通路約 ¥58,000
A8: 電池月費（202Wh） | B8: =電池訂閱費!C61 -> 1280 | F8: 電池訂閱費表
A9: 電池月費（360Wh，載童版） | B9: =電池訂閱費!D61 -> 1680 | F9: 電池訂閱費表
A10: 分期回數 | B10: 36 | F10: JACCS／Orico ショッピングローン；Panasonic 官網、ハヤサカ最多 36 回無金利
A11: 消費者分期利率（無金利活動） | B11: 0 | F11: 通路負擔金利
A12: 通路負擔之分期手數料率（佔本金） | B12: 0.08 | F12: 假設：36 回無金利活動由通路支付金融公司約 8–12%
A13: NORUDE ViVi SX 整車訂閱月費 | B13: 2890 | F13: V3 分頁 9；36 月 ¥104,040，期末還車
A14: NORUDE 子乗せ月費 | B14: 5690 | F14: V3 分頁 9
A15: 員工邊際稅率（所得稅 + 住民稅） | B15: 0.2 | F15: 年收 500–700 萬圓區間概算；用於現物給與課稅
A16: 法人租賃：年利率 | B16: 0.05 | F16: 假設
A17: 法人租賃：期末殘值率（車體） | B17: 0.1 | F17: 假設；中國製車在日本二手市場近乎無行情
A18: 法人租賃：保養與保險（¥/月） | B18: 300 | F18: 假設；Yamaha PAS リース含保養保險
A19: 法人通路：訂閱呆帳率 | B19: 0.01 | F19: 公司統一請款
A20: 法人通路：訂閱 CAC（¥） | B20: 1000 | F20: B2B2C 通路，趨近零
A21: ふるさと納税：返礼品率上限 | B21: 0.3 | F21: 總務省基準：返礼品 ≤ 寄付額 3 割、含送料事務 ≤ 5 割
... A25: 自治體子乗せ補助（¥） | B25: 40000 | F25: 赤穂市 ¥4 萬、輕井澤町 ¥5 萬、廣島府中町 2026 新設；多要求型式認定／BAA
A27: B. 消費者視角：每月支出與 3 年總成本（平地版，202Wh）
A28: 路徑 | B28: 月付（¥） | C28: 前置費用（¥） | D28: 3 年總支出（¥） | E28: 期末車體歸屬 | F28: 說明
A29: ① 通路零利率分期 36 回 + 電池訂閱 | B29: =B6*(1+B11)/B10+B8 -> 2631.8365 | C29: 0 | D29: =B6*(1+B11)+B8*36 -> 94746.115 | E29: 消費者 | F29: 主打對比：與 NORUDE 同價位，但車歸自己、電池永遠有效
A30: ② A 法人付電池訂閱、員工自買車體（分期） | B30: =B6/B10+B8*B15 -> 1607.8365 | C30: 0 | D30: =B30*36 -> 57882.115 | E30: 員工 | F30: 員工月付 = 車體分期 + 電池訂閱現物給與之稅負；公司付電池月費
A31: ② B 法人全額租賃（車體 + 電池 + 保養），員工負擔課稅 | B31: =((B6*(1-B17))/B10+B6*B16/12+B8+B18)*B15 -> 599.88567 | C31: 0 | D31: =B31*36 -> 21595.884 | E31: 公司（期末殘值） | F31: 公司月付見 C 段；員工僅負擔現物給與稅
A32: ③ ふるさと納税（車體 + 首年電池訂閱券） | B32: =B8*(36-B23)/36 -> 853.33333 | C32: =B22 -> 2000 | D32: =B22+B8*(36-B23) -> 32720 | E32: 消費者 | F32: 前提：寄付額落在個人控除上限內（見 D 段），且產品符合地場產品基準
A33: 對照：NORUDE ViVi SX 整車訂閱 | B33: =B13 -> 2890 | C33: 3520 | D33: =B13*36+C33 -> 107560 | E33: NORUDE（還車） | F33: 事務手數料 ¥3,520；盜難補償 ¥700/月另計
A34: 對照：PELTECH 型式認定車買斷 ¥89,980 | B34: =89980/36 -> 2499.4444 | C34: 89980 | D34: =89980+5000*3 -> 104980 | E34: 消費者 | F34: 含年維護 ¥5,000；第 4 年換電池 ¥35,000 未計入 3 年
A35: ① 對 NORUDE 之 3 年差額（負值 = 本案較省） | D35: =D29-D33 -> -12813.885 | F35: 且車體歸消費者
A37: B-2. 載童版（360Wh）：分期 + 自治體補助
A38: 路徑 | B38: 月付（¥） | C38: 前置費用（¥） | D38: 3 年總支出（¥） | E38: 期末車體歸屬 | F38: 說明
A39: ① 載童版分期 36 回 + 360Wh 訂閱 | B39: =B7/B10+B9 -> 3291.1111 | C39: 0 | D39: =B7+B9*36 -> 118480 | E39: 消費者 | F39: 對照 NORUDE 子乗せ ¥5,690/月、Panasonic Gyutto ¥170,000
A40: ① 載童版 + 自治體補助（補助後車體一次付清） | B40: =B9 -> 1680 | C40: =MAX(B7-B25,0) -> 18000 | D40: =C40+B9*36 -> 78480 | E40: 消費者 | F40: 限有補助之自治體；須型式認定 + BAA
A41: 對照：NORUDE 子乗せ | B41: =B14 -> 5690 | C41: 3520 | D41: =B14*36+C41 -> 208360 | E41: NORUDE（還車）
A43: C. 營運商／通路視角：每戶 36 月淨值（電池訂閱）與車體通路成本
A44: 路徑 | B44: 訂閱月費（¥） | C44: 呆帳率 | D44: CAC（¥） | E44: 36 月單戶淨值（¥） | F44: 車體側成本 / 說明
A45: ① 通路分期（B2C） | B45: =B8 -> 1280 | C45: =假設!$B$75 -> 0.03 | D45: =假設!$B$83 -> 3000 | E45: =(B8/(1+假設!$B$74)*(1-假設!$B$75-假設!$B$76)-(假設!$B$78+假設!$B$79+假設!$B$77)-電池訂閱費!C54-電池訂閱費!C53)*假設!$B$82+電池訂閱費!C49*假設!$B$84-電池訂閱費!C51-假設!$B$83 -> 11153.926 | F45: ="車體通路須負擔分期手數料 ¥"&TEXT(B6*B12,"#,##0")&"/台（佔零售 "&TEXT(B12,"0%")&"）" -> 車體通路須負擔分期手數料 ¥3,893/台（佔零售 8%）
A46: ② 法人通路（B2B2C） | B46: =B8 -> 1280 | C46: =B19 -> 0.01 | D46: =B20 -> 1000 | E46: =(B8/(1+假設!$B$74)*(1-B19-假設!$B$76)-(假設!$B$78+假設!$B$79+假設!$B$77)-電池訂閱費!C54-電池訂閱費!C53)*假設!$B$82+電池訂閱費!C49*假設!$B$84-電池訂閱費!C51-B20 -> 13991.744 | F46: 公司統一請款、呆帳趨近零；Yamaha PAS リース 3 台起、NORUDE for Biz 為現成對照
A47: ③ ふるさと納税（首年由自治體支付，次年起 B2C） | B47: =B8 -> 1280 | C47: =假設!$B$75 -> 0.03 | D47: 0 | E47: =(B8/(1+假設!$B$74)*(1-假設!$B$75-假設!$B$76)-(假設!$B$78+假設!$B$79+假設!$B$77)-電池訂閱費!C54-電池訂閱費!C53)*假設!$B$82+電池訂閱費!C49*假設!$B$84-電池訂閱費!C51-0 -> 14153.926 | F47: CAC 為零（自治體通路）；但須在地組裝加價、且首年訂閱以躉售價賣給自治體
A48: ② 對 ① 之單戶淨值增幅 | E48: =E46-E45 -> 2837.8182 | F48: 呆帳與 CAC 下降的合計效果
A49: ② B 公司月付（全額租賃） | B49: =((B6*(1-B17))/B10+B6*B16/12+B8+B18) -> 2999.4284 | F49: ＝ 車體 ×(1−殘值)÷36 + 利息 + 電池月費 + 保養；對照 MOVE.eBike 法人月額 ¥14,000 起
A51: D. ふるさと納税可行性檢核：需要的寄付額與年收門檻
A52: 項目 | B52: 值（¥） | F52: 說明
A53: 返礼品價值 = 車體 + 首年電池訂閱 + 在地組裝加價 | B53: =B6+B8*B23+B24 -> 70026.115 | F53: 以零售價計（自治體調達價通常低於零售）
A54: 所需寄付額 = 返礼品價值 ÷ 30% | B54: =B53/B21 -> 233420.38 | F54: 總務省 3 割規則
A55: 消費者實際成本（寄付在控除上限內） | B55: =B22 -> 2000 | F55: ¥2,000 自付；其餘為所得稅與住民稅扣除
A56: 年收（萬圓，單身無扶養） | B56: 控除上限概算（¥） | C56: 可否全額扣除 | D56: 超出部分（¥） | F56: 說明
A57: 300 | B57: 28000 | C57: =IF(B57>=$B$54,"可","否") -> 否 | D57: =MAX($B$54-B57,0) -> 205420.38 | F57: 控除上限為概算（ふるさと納税ポータル試算），實際依家庭狀況；超出部分為消費者自付
A58: 500 | B58: 61000 | C58: =IF(B58>=$B$54,"可","否") -> 否 | D58: =MAX($B$54-B58,0) -> 172420.38 | F58: 控除上限為概算（ふるさと納税ポータル試算），實際依家庭狀況；超出部分為消費者自付
A59: 700 | B59: 108000 | C59: =IF(B59>=$B$54,"可","否") -> 否 | D59: =MAX($B$54-B59,0) -> 125420.38 | F59: 控除上限為概算（ふるさと納税ポータル試算），實際依家庭狀況；超出部分為消費者自付
A60: 1000 | B60: 176000 | C60: =IF(B60>=$B$54,"可","否") -> 否 | D60: =MAX($B$54-B60,0) -> 57420.384 | F60: 控除上限為概算（ふるさと納税ポータル試算），實際依家庭狀況；超出部分為消費者自付
A61: 1500 | B61: 389000 | C61: =IF(B61>=$B$54,"可","否") -> 可 | D61: =MAX($B$54-B61,0) -> 0 | F61: 控除上限為概算（ふるさと納税ポータル試算），實際依家庭狀況；超出部分為消費者自付
A62: 判讀 | F62: 車體便宜反而讓ふるさと納税不划算：寄付額是產品價值的 3.3 倍，只有高年收者能全額扣除；且地場產品基準要求在地製造，達方無日本工廠。此路徑僅在「日本最終組裝 + 鎖定年收 1,000 萬圓以上家庭」時成立。

Sheet 三變體
A1: 三個產品變體：平地版／日本平地版／坡地載童版
A2: 同一車體平台，差異化延到總裝段。材料增額對配置 C（不含電池、不含充電器）計；RMB。
A4: A. 規格矩陣
A5: 項目 | B5: 平地版（歐洲／台灣） | C5: 日本平地版 | D5: 坡地載童版（日本、坡地城市） | E5: 說明
A6: 感測 | B6: 踏頻 + IMU + 相電流估算（B 方案） | C6: 中軸扭力感測（法規） | D6: 中軸扭力感測 | E6: 日本助力比以人力為分母，踏頻不能取證
A7: 控制邏輯 | B7: 速度保持：目標 20/22/25 km/h，22–25 線性衰減 | C7: 2:1 → 0 線性遞減（10–24 km/h） | D7: 同日本平地版 | E7: 兩套韌體皆鎖 OTP，出廠依市場燒錄
A8: 輪徑／齒比 | B8: 26 吋或 700c、44/16 | C8: 26 吋、44/16 | D8: 20–24 吋、42/18 | E8: 小輪徑 + 低齒比補單速在坡地的踏頻與扭矩
A9: 馬達 | B9: 商品化 250W 齒輪輪轂 30–32 N·m | C9: 同左 | D9: 40–45 N·m 級齒輪輪轂，含溫度感測與降額 | E9: 載童 125 kg 爬 10% 坡需 33 N·m（20 吋）
A10: 煞車 | B10: V 煞前後 | C10: V 煞前後 | D10: 後機械碟 + 前 V | E10: 30 kg 整車加小孩下坡，V 煞不過 JIS
A11: 車架 | B11: 公版鋁／鋼、無內走線 | C11: 公版 | D11: 通過幼児二人同乗基準之公版（BAA／SG）、両立スタンド、把手鎖 | E11: 仍是零開模公版
A12: 電池訂閱層級 | B12: 180／252Wh | C12: 144／202Wh | D12: 360Wh（更換週期抓 36 月） | E12: 電池在訂閱側切換，不動出廠價
A13: 目標市場 | B13: 台北、阿姆斯特丹、柏林等平地都會 | C13: 東京 23 區、大阪 | D13: 橫濱、神戶、長崎；日本載童家庭 | E13: 長坡（>10 分鐘連續爬升）不保證
A15: B. 材料增額與出廠價（RMB，對配置 C）
A16: 項目 | B16: 平地版 | C16: 日本平地版 | D16: 坡地載童版 | E16: 依據
A17: 配置 C 材料（不含電池、充電器） | B17: =入手價!B8 -> 799.216 | C17: =入手價!B8 -> 799.216 | D17: =入手價!B8 -> 799.216 | E17: 入手價表
A18: 扭力感測淨增額 | B18: 0 | C18: =假設!$B$14 -> 160 | D18: =假設!$B$14 -> 160 | E18: V3 分頁 7
A19: 日本非 BOM 增額（認定／PSE／說明書／OTP） | B19: 0 | C19: =假設!$B$15 -> 7.3 | D19: =假設!$B$15 -> 7.3 | E19: V3 分頁 7
A20: 馬達升級 40–45 N·m 級 | B20: 0 | C20: 0 | D20: 80 | E20: 假設：商品化 45 N·m 齒輪輪轂 RMB 280–300 vs 205
A21: 後機械碟煞（含碟煞座） | B21: 0 | C21: 0 | D21: 54 | E21: V3 分頁 2：機械碟 vs V 煞差 54
A22: 子乗せ車架強度與両立スタンド、把手鎖 | B22: 0 | C22: 0 | D22: 90 | E22: 假設：車架 +60、支撐與配件 +30
A23: 20 吋輪組差額 | B23: 0 | C23: 0 | D23: -10 | E23: 20 吋成輪較 26 吋便宜
A24: 型式認定 + 子乗せ檢測攤提 | B24: 0 | C24: 0 | D24: 8 | E24: ¥2–3M ÷ 2 萬台 ≈ ¥120 ≈ RMB 5–8
A25: 材料合計（RMB） | B25: =B17+SUM(B18:B24) -> 799.216 | C25: =C17+SUM(C18:C24) -> 966.516 | D25: =D17+SUM(D18:D24) -> 1188.516
A26: 出廠價 @ODM 13%（RMB，不含電池） | B26: =(B25+假設!$B$7)/(1-假設!$B$8) -> 943.92644 | C26: =(C25+假設!$B$7)/(1-假設!$B$8) -> 1136.2253 | D26: =(D25+假設!$B$7)/(1-假設!$B$8) -> 1391.3977
A27: 出廠價 @ODM 18%（RMB） | B27: =(B25+假設!$B$7)/(1-假設!$B$9) -> 1001.4829 | C27: =(C25+假設!$B$7)/(1-假設!$B$9) -> 1205.5073 | D27: =(D25+假設!$B$7)/(1-假設!$B$9) -> 1476.239
A28: 出廠價 @13%（NT$） | B28: =B26*假設!$B$20 -> 4285.426 | C28: =C26*假設!$B$20 -> 5158.4628 | D28: =D26*假設!$B$20 -> 6316.9456
A29: 出廠價 @13%（JPY） | B29: =B26*假設!$B$21 -> 22182.271 | C29: =C26*假設!$B$21 -> 26701.294 | D29: =D26*假設!$B$21 -> 32697.846
A30: 對平地版出廠價之溢出 | B30: =B26/$B$26-1 -> 0 | C30: =C26/$B$26-1 -> 0.20372229 | D30: =D26/$B$26-1 -> 0.47405311
A32: C. 各市場零售（含稅）與電池訂閱
A33: 項目 | B33: 平地版 | C33: 日本平地版 | D33: 坡地載童版 | E33: 公式
A34: 歐洲 DTC 零售 €（台越製） | B34: =(B26/假設!$B$19*(1+假設!$B$25)+假設!$B$26)/(1-假設!$B$27)*(1+假設!$B$46) -> 184.2571 | C34: — | D34: =(D26/假設!$B$19*(1+假設!$B$25)+假設!$B$26)/(1-假設!$B$27)*(1+假設!$B$46) -> 264.66169 | E34: 入手價表結構；坡地版在歐洲坡地城市亦適用
A35: 台灣 DTC 零售 NT$ | B35: =(B28+150)/(1-假設!$B$30)*(1+假設!$B$31) -> 7164.919 | C35: — | D35: =(D28+150)/(1-假設!$B$30)*(1+假設!$B$31) -> 10446.604 | E35: 台灣坡地（北投、基隆）可用坡地版
A36: 日本 PB 通路零售 ¥（税込） | B36: — | C36: =((C29*(1+假設!$B$32)+假設!$B$33+假設!$B$34+假設!$B$35+假設!$B$36)-假設!$B$37)/(1-假設!$B$38)*(1+假設!$B$41) -> 48666.115 | D36: =((D29*(1+假設!$B$32)+假設!$B$33+假設!$B$34+假設!$B$35+假設!$B$36)-假設!$B$37)/(1-假設!$B$38)*(1+假設!$B$41) -> 58466.194 | E36: V3 分頁 8 情境 3；載童版不含兒童座椅
A37: 日本 BESV 通路零售 ¥（15% + 22%） | B37: — | C37: =(C29*(1+假設!$B$32)+假設!$B$33+假設!$B$34+假設!$B$35+假設!$B$36)/(1-假設!$B$39)/(1-假設!$B$40)*(1+假設!$B$41) -> 57188.96 | D37: =(D29*(1+假設!$B$32)+假設!$B$33+假設!$B$34+假設!$B$35+假設!$B$36)/(1-假設!$B$39)/(1-假設!$B$40)*(1+假設!$B$41) -> 67535.951 | E37: V3 分頁 8 情境 2
A38: 電池訂閱月費（建議定價） | B38: ="€"&TEXT(電池訂閱費!C19,"0.0")&" / NT$"&TEXT(電池訂閱費!C40,"#,##0") -> €9.9 / NT$299 | C38: ="¥"&TEXT(電池訂閱費!C61,"#,##0") -> ¥1,280 | D38: ="¥"&TEXT(電池訂閱費!D61,"#,##0") -> ¥1,680 | E38: 電池訂閱費表
A39: 日本對照（税込） | B39: — | C39: Cainz PB ¥59,800／Panasonic ビビ EYX ¥89,800 | D39: Panasonic Gyutto ¥170,000／Yamaha PAS Kiss ¥187,000 | E39: V3 分頁 8 C 段
A41: D. 物理檢核：輪端扭矩、踏頻與騎士出力（藍字可改）
A42: 參數 | B42: 值 | E42: 說明
A43: 重力加速度 g | B43: 9.81 | E43: m/s²
A44: 滾動阻力係數 Crr | B44: 0.006 | E44: 盡調報告假設
A45: 空氣阻力（低速，N） | B45: 2 | E45: 8–10 km/h 時約 2 N
A46: 26 吋輪半徑（m） | B46: 0.33 | E46: 700c 亦約 0.33–0.34
A47: 20 吋輪半徑（m） | B47: 0.254
A48: 坡地檢核車速（km/h） | B48: 8 | E48: 日本 10 km/h 以下適用 2:1 上限
A49: 日本騎士最低出力占比 | B49: 0.3333 | E49: 助力比 1:2 → 騎士 ≥ 1/3
A50: 商品化輪轂輪端扭矩上限（N·m） | B50: 32 | E50: Bafang RM G010 級
A51: 45 N·m 級輪轂上限（N·m） | B51: 45
A53: 情境 | B53: 總重 kg | C53: 坡度 | D53: 輪端扭矩需求 26 吋（N·m） | E53: 輪端扭矩需求 20 吋（N·m）
A54: 平地通勤 | B54: 100 | C54: 0.08 | D54: =(B54*$B$43*(C54+$B$44)+$B$45)*$B$46 -> 28.50078 | E54: =(B54*$B$43*(C54+$B$44)+$B$45)*$B$47 -> 21.936964
A55: 平地通勤 | B55: 100 | C55: 0.1 | D55: =(B55*$B$43*(C55+$B$44)+$B$45)*$B$46 -> 34.97538 | E55: =(B55*$B$43*(C55+$B$44)+$B$45)*$B$47 -> 26.920444
A56: 載童 | B56: 125 | C56: 0.08 | D56: =(B56*$B$43*(C56+$B$44)+$B$45)*$B$46 -> 35.460975 | E56: =(B56*$B$43*(C56+$B$44)+$B$45)*$B$47 -> 27.294205
A57: 載童 | B57: 125 | C57: 0.1 | D57: =(B57*$B$43*(C57+$B$44)+$B$45)*$B$46 -> 43.554225 | E57: =(B57*$B$43*(C57+$B$44)+$B$45)*$B$47 -> 33.523555
A58: 判定：商品化 32 N·m 在 26 吋只夠 100 kg／8%；載童 125 kg／10% 需 45 N·m 級或改 20 吋
A60: 日本 2:1 下騎士出力（載童 125 kg、8% 坡、8 km/h） | B60: 26 吋 44/16 | C60: 26 吋 38/18 | D60: 20 吋 42/18 | E60: 說明
A61: 總功率需求 W | B61: =(B56*$B$43*(C56+$B$44)+$B$45)*$B$48/3.6 -> 238.79444 | C61: =(B56*$B$43*(C56+$B$44)+$B$45)*$B$48/3.6 -> 238.79444 | D61: =(B56*$B$43*(C56+$B$44)+$B$45)*$B$48/3.6 -> 238.79444
A62: 騎士出力 W（≥ 1/3） | B62: =B61*$B$49 -> 79.590188 | C62: =C61*$B$49 -> 79.590188 | D62: =D61*$B$49 -> 79.590188
A63: 輪周長 m | B63: =2*PI()*$B$46 -> 2.0734512 | C63: =2*PI()*$B$46 -> 2.0734512 | D63: =2*PI()*$B$47 -> 1.5959291
A64: 齒比 | B64: =44/16 -> 2.75 | C64: =38/18 -> 2.1111111 | D64: =42/18 -> 2.3333333
A65: 8 km/h 踏頻 rpm | B65: =$B$48*1000/60/B63/B64 -> 23.383646 | C65: =$B$48*1000/60/C63/C64 -> 30.460276 | D65: =$B$48*1000/60/D63/D64 -> 35.805387
A66: 騎士曲柄扭矩 N·m | B66: =B62/(B65*2*PI()/60) -> 32.502643 | C66: =C62/(C65*2*PI()/60) -> 24.951524 | D66: =D62/(D65*2*PI()/60) -> 21.226703 | E66: 一般通勤者持續上限約 25–30 N·m；20 吋 42/18 落在可行區
A67: 70 rpm 巡航速度 km/h | B67: =70*B64*B63*60/1000 -> 23.948361 | C67: =70*C64*C63*60/1000 -> 18.3846 | D67: =70*D64*D63*60/1000 -> 15.640105 | E67: 日本媽媽車巡航 15–18 km/h

Sheet 五年財務
A1: 五年財務計畫（達方視角，NT$ 百萬）
A2: 硬體以出廠價加達方毛利賣給通路；電池訂閱由達方（或 SPV）持有資產並收月費。藍字為量與比率假設。
A4: A. 量與組合假設
A5: 項目 | B5: 2027 | C5: 2028 | D5: 2029 | E5: 2030 | F5: 2031 | G5: 說明
A6: 整車出貨量（台） | B6: 8000 | C6: 25000 | D6: 50000 | E6: 80000 | F6: 110000 | G6: 保守：原提案 Y5 45 萬台被盡調否決；30k 為出廠價達標門檻
A7: 歐洲平地版占比 | B7: 0.5 | C7: 0.5 | D7: 0.5 | E7: 0.5 | F7: 0.5
A8: 日本平地版占比 | B8: 0.18 | C8: 0.18 | D8: 0.18 | E8: 0.18 | F8: 0.18
A9: 日本載童版占比 | B9: 0.12 | C9: 0.12 | D9: 0.12 | E9: 0.12 | F9: 0.12
A10: 台灣／其他平地版占比 | B10: 0.2 | C10: 0.2 | D10: 0.2 | E10: 0.2 | F10: 0.2
A11: 電池訂閱附加率（未買斷比例） | B11: 0.85 | C11: 0.85 | D11: 0.85 | E11: 0.85 | F11: 0.85 | G11: 提供買斷選項；假設 15% 買斷
A12: 訂戶年留存率 | B12: 0.8 | C12: 0.8 | D12: 0.8 | E12: 0.8 | F12: 0.8 | G12: 平均壽命 36 月 ≈ 年留存 75–80%
A13: 達方硬體毛利率（對出廠價加成） | B13: 0.2 | C13: 0.2 | D13: 0.2 | E13: 0.2 | F13: 0.2 | G13: 品牌／整合／保固；8/28 門檻 ≥ 15%
A15: B. 單價（NT$／台或／戶，連動模型）
A16: 項目 | B16: 歐洲平地 | C16: 日本平地 | D16: 日本載童 | E16: 台灣平地 | F16: 加權 | G16: 說明
A17: 出廠價（NT$） | B17: =三變體!B28 -> 4285.426 | C17: =三變體!C28 -> 5158.4628 | D17: =三變體!D28 -> 6316.9456 | E17: =三變體!B28 -> 4285.426 | F17: =B17*$B$7+C17*$B$8+D17*$B$9+E17*$B$10 -> 4686.355 | G17: 三變體表；加權以 2027 組合計
A18: 電池月費（NT$，含稅） | B18: =電池訂閱費!C19*假設!$B$19*假設!$B$20 -> 485.4168 | C18: =電池訂閱費!C61/假設!$B$21*假設!$B$20 -> 247.28511 | D18: =電池訂閱費!D61/假設!$B$21*假設!$B$20 -> 324.5617 | E18: =電池訂閱費!C40 -> 299 | F18: =B18*$B$7+C18*$B$8+D18*$B$9+E18*$B$10 -> 385.96712 | G18: €9.9／¥1,280／¥1,680／NT$299
A19: 月費淨額係數（除 VAT／消費稅） | B19: =1/(1+假設!$B$46) -> 0.84033613 | C19: =1/(1+假設!$B$41) -> 0.90909091 | D19: =1/(1+假設!$B$41) -> 0.90909091 | E19: =1/(1+假設!$B$31) -> 0.95238095 | F19: =B19*$B$7+C19*$B$8+D19*$B$9+E19*$B$10 -> 0.88337153
A20: 每戶每月現金成本（NT$，③④⑤⑥ + 呆帳金流） | B20: =(電池訂閱費!C12+電池訂閱費!C13+電池訂閱費!C19/(1+假設!$B$46)*(假設!$B$47+假設!$B$48))*假設!$B$19*假設!$B$20 -> 186.47491 | C20: =(電池訂閱費!C54+電池訂閱費!C55+電池訂閱費!C61/(1+假設!$B$41)*(假設!$B$75+假設!$B$76))/假設!$B$21*假設!$B$20 -> 103.6637 | D20: =(電池訂閱費!D54+電池訂閱費!D55+電池訂閱費!D61/(1+假設!$B$41)*(假設!$B$75+假設!$B$76))/假設!$B$21*假設!$B$20 -> 120.3341 | E20: =電池訂閱費!C33+電池訂閱費!C34+電池訂閱費!C40/(1+假設!$B$31)*(假設!$B$61+假設!$B$62) -> 110.22742 | F20: =B20*$B$7+C20*$B$8+D20*$B$9+E20*$B$10 -> 148.3825 | G20: 更換準備 + 失竊／客服／物流 + 呆帳金流；資產與 CAC 另列
A21: 每戶電池 + 充電器資產（NT$） | B21: =電池訂閱費!C9*假設!$B$19*假設!$B$20 -> 2007.0341 | C21: =電池訂閱費!C51/假設!$B$21*假設!$B$20 -> 1658.1908 | D21: =電池訂閱費!D51/假設!$B$21*假設!$B$20 -> 2239.1856 | E21: =電池訂閱費!C30 -> 1808.402 | F21: =B21*$B$7+C21*$B$8+D21*$B$9+E21*$B$10 -> 1932.3741 | G21: 資本支出；4 年折舊
A22: 每戶 CAC（NT$） | B22: =假設!$B$55*假設!$B$19*假設!$B$20 -> 1470.96 | C22: =假設!$B$83/假設!$B$21*假設!$B$20 -> 579.57447 | D22: =假設!$B$83/假設!$B$21*假設!$B$20 -> 579.57447 | E22: =假設!$B$69 -> 800 | F22: =B22*$B$7+C22*$B$8+D22*$B$9+E22*$B$10 -> 1069.3523 | G22: 隨車成交
A24: C. 營運費用假設（NT$ 百萬／年）
A25: 項目 | B25: 2027 | C25: 2028 | D25: 2029 | E25: 2030 | F25: 2031 | G25: 說明
A26: 三電 RD（韌體、控制器、電池包） | B26: 5 | C26: 5 | D26: 8 | E26: 8 | F26: 8 | G26: 8/28：RD NT$3–5M 上限起步
A27: APP／雲端／資料團隊 | B27: 6 | C27: 8 | D27: 8 | E27: 10 | F27: 10 | G27: BOM 報告：完整 IoT 平台 NT$12M；本案 BLE + SoH 較輕
A28: 認證與模具（EN 15194／UN38.3／日本型式認定 ×3／PSE） | B28: 4 | C28: 4 | D28: 3 | E28: 1 | F28: 1 | G28: US$130k + ¥2–3M + 模具
A29: 翻新中心與逆物流建置（歐、日各一） | B29: 3 | C29: 10 | D29: 5 | E29: 3 | F29: 3 | G29: 含治具、危險品倉儲
A30: 行銷與通路（佔硬體營收） | B30: 0.08 | C30: 0.06 | D30: 0.05 | E30: 0.05 | F30: 0.05 | G30: 比率；DTC 與 B2B2C 混合
A31: 管理與其他（佔總營收） | B31: 0.04 | C31: 0.03 | D31: 0.03 | E31: 0.03 | F31: 0.03 | G31: 比率
A33: D. 損益與現金流（NT$ 百萬）
A34: 項目 | B34: 2027 | C34: 2028 | D34: 2029 | E34: 2030 | F34: 2031 | G34: 公式
A35: 新增訂戶（戶） | B35: =B6*B11 -> 6800 | C35: =C6*C11 -> 21250 | D35: =D6*D11 -> 42500 | E35: =E6*E11 -> 68000 | F35: =F6*F11 -> 93500 | G35: 出貨 × 附加率
A36: 期末在訂戶（戶） | B36: =B35 -> 6800 | C36: =B36*C12+C35 -> 26690 | D36: =C36*D12+D35 -> 63852 | E36: =D36*E12+E35 -> 119081.6 | F36: =E36*F12+F35 -> 188765.28 | G36: 上期 × 留存 + 新增
A37: 平均在訂戶（戶） | B37: =B36/2 -> 3400 | C37: =(B36+C36)/2 -> 16745 | D37: =(C36+D36)/2 -> 45271 | E37: =(D36+E36)/2 -> 91466.8 | F37: =(E36+F36)/2 -> 153923.44
A38: 硬體營收 | B38: =B6*$F$17*(1+B13)/1000000 -> 44.989008 | C38: =C6*$F$17*(1+C13)/1000000 -> 140.59065 | D38: =D6*$F$17*(1+D13)/1000000 -> 281.1813 | E38: =E6*$F$17*(1+E13)/1000000 -> 449.89008 | F38: =F6*$F$17*(1+F13)/1000000 -> 618.59886 | G38: 出貨 × 出廠價 × (1 + 達方毛利)
A39: 硬體成本 | B39: =B6*$F$17/1000000 -> 37.49084 | C39: =C6*$F$17/1000000 -> 117.15887 | D39: =D6*$F$17/1000000 -> 234.31775 | E39: =E6*$F$17/1000000 -> 374.9084 | F39: =F6*$F$17/1000000 -> 515.49905 | G39: 以出廠價採購
A40: 訂閱營收（淨額） | B40: =B37*$F$18*$F$19*12/1000000 -> 13.910857 | C40: =C37*$F$18*$F$19*12/1000000 -> 68.510969 | D40: =D37*$F$18*$F$19*12/1000000 -> 185.22306 | E40: =E37*$F$18*$F$19*12/1000000 -> 374.22987 | F40: =F37*$F$18*$F$19*12/1000000 -> 629.76674 | G40: 平均戶 × 月費淨額 × 12
A41: 訂閱現金成本 | B41: =B37*$F$20*12/1000000 -> 6.0540059 | C41: =C37*$F$20*12/1000000 -> 29.815979 | D41: =D37*$F$20*12/1000000 -> 80.609088 | E41: =E37*$F$20*12/1000000 -> 162.86487 | F41: =F37*$F$20*12/1000000 -> 274.07453
A42: 訂閱 CAC | B42: =B35*$F$22/1000000 -> 7.2715959 | C42: =C35*$F$22/1000000 -> 22.723737 | D42: =D35*$F$22/1000000 -> 45.447474 | E42: =E35*$F$22/1000000 -> 72.715959 | F42: =F35*$F$22/1000000 -> 99.984444
A43: 電池資產折舊（4 年） | B43: =B35*$F$21/4/1000000 -> 3.2850359 | C43: =B35*$F$21/4/1000000+C35*$F$21/4/1000000 -> 13.550773 | D43: =B35*$F$21/4/1000000+C35*$F$21/4/1000000+D35*$F$21/4/1000000 -> 34.082248 | E43: =B35*$F$21/4/1000000+C35*$F$21/4/1000000+D35*$F$21/4/1000000+E35*$F$21/4/1000000 -> 66.932607 | F43: =C35*$F$21/4/1000000+D35*$F$21/4/1000000+E35*$F$21/4/1000000+F35*$F$21/4/1000000 -> 108.81681 | G43: 新增訂戶資產 ÷ 4，攤 4 年
A44: 總營收 | B44: =B38+B40 -> 58.899865 | C44: =C38+C40 -> 209.10162 | D44: =D38+D40 -> 466.40436 | E44: =E38+E40 -> 824.11994 | F44: =F38+F40 -> 1248.3656
A45: 毛利（硬體 + 訂閱，含折舊） | B45: =B38-B39+B40-B41-B42-B43 -> 4.7983869 | C45: =C38-C39+C40-C41-C42-C43 -> 25.852255 | D45: =D38-D39+D40-D41-D42-D43 -> 71.947796 | E45: =E38-E39+E40-E41-E42-E43 -> 146.69811 | F45: =F38-F39+F40-F41-F42-F43 -> 249.99076
A46: 毛利率 | B46: =IF(B44>0,B45/B44,0) -> 0.081466859 | C46: =IF(C44>0,C45/C44,0) -> 0.12363489 | D46: =IF(D44>0,D45/D44,0) -> 0.15426056 | E46: =IF(E44>0,E45/E44,0) -> 0.17800578 | F46: =IF(F44>0,F45/F44,0) -> 0.20025444
A47: RD + APP + 認證 + 翻新建置 | B47: =B26+B27+B28+B29 -> 18 | C47: =C26+C27+C28+C29 -> 27 | D47: =D26+D27+D28+D29 -> 24 | E47: =E26+E27+E28+E29 -> 22 | F47: =F26+F27+F28+F29 -> 22
A48: 行銷與通路 | B48: =B38*B30 -> 3.5991206 | C48: =C38*C30 -> 8.435439 | D48: =D38*D30 -> 14.059065 | E48: =E38*E30 -> 22.494504 | F48: =F38*F30 -> 30.929943
A49: 管理與其他 | B49: =B44*B31 -> 2.3559946 | C49: =C44*C31 -> 6.2730486 | D49: =D44*D31 -> 13.992131 | E49: =E44*E31 -> 24.723598 | F49: =F44*F31 -> 37.450968
A50: EBIT | B50: =B45-B47-B48-B49 -> -19.156728 | C50: =C45-C47-C48-C49 -> -15.856233 | D50: =D45-D47-D48-D49 -> 19.8966 | E50: =E45-E47-E48-E49 -> 77.480011 | F50: =F45-F47-F48-F49 -> 159.60985
A51: EBIT 率 | B51: =IF(B44>0,B50/B44,0) -> -0.32524231 | C51: =IF(C44>0,C50/C44,0) -> -0.075830273 | D51: =IF(D44>0,D50/D44,0) -> 0.042659551 | E51: =IF(E44>0,E50/E44,0) -> 0.094015455 | F51: =IF(F44>0,F50/F44,0) -> 0.12785505
A52: 電池資本支出 | B52: =B35*$F$21/1000000 -> 13.140144 | C52: =C35*$F$21/1000000 -> 41.062949 | D52: =D35*$F$21/1000000 -> 82.125898 | E52: =E35*$F$21/1000000 -> 131.40144 | F52: =F35*$F$21/1000000 -> 180.67698 | G52: 新增訂戶 × 每戶資產
A53: 營運現金流（EBIT + 折舊 − 電池資本支出） | B53: =B50+B43-B52 -> -29.011836 | C53: =C50+C43-C52 -> -43.368409 | D53: =D50+D43-D52 -> -28.14705 | E53: =E50+E43-E52 -> 13.011181 | F53: =F50+F43-F52 -> 87.749686
A54: 累計現金流 | B54: =B53 -> -29.011836 | C54: =B54+C53 -> -72.380245 | D54: =C54+D53 -> -100.52729 | E54: =D54+E53 -> -87.516113 | F54: =E54+F53 -> 0.2335724 | G54: 最低點 = 資金需求峰值（未含營運資金）
A55: 電池車隊資產（毛額，期末） | B55: =B52 -> 13.140144 | C55: =B52+C52 -> 54.203093 | D55: =B52+C52+D52 -> 136.32899 | E55: =B52+C52+D52+E52 -> 267.73043 | F55: =B52+C52+D52+E52+F52 -> 448.4074 | G55: 可由 SPV／租賃夥伴持有
A56: 資金需求峰值（累計現金流最低點） | B56: =-MIN(B54:F54) -> 100.52729 | G56: 若電池資產由 SPV 持有，達方峰值 ≈ 此值 − 電池資本支出累計
A57: 若 SPV 持有電池：達方累計現金流最低點 | B57: =MIN(B54+B55,C54+C55,D54+D55,E54+E55,F54+F55) -> -18.177152 | G57: SPV 融資成本未計

Sheet 兩條路對照
A1: 兩條路五年對照與決策門檻：合規電池平台 + OEM 服務（C1） vs 低價整車 + 電池訂閱（B2C）
A2: C1 參數取自 V4 分頁 11；B2C 連動五年財務分頁並以量級倍數做情境。NT$ 百萬除非另註。藍字可改。
A4: A. C1 假設（V4 分頁 11）
A5: 參數 | B5: 值 | G5: 來源
A6: 三電成本 €/台 | B6: 55 | G6: RMB 595 ÷ 10.8
A7: 賣 OEM 毛利率 | B7: 0.25 | G7: Tier 1 常見 20–30%
A8: 服務合約 €/台/年 | B8: 10 | G8: 護照、EPR、備品、SoH、回收；無公開價格
A9: 服務成本 €/台/年 | B9: 4.5 | G9: 系統、行政、備品攤提
A10: 在保年數（服務收費期） | B10: 5 | G10: 備品義務 5 年
A11: EUR/NTD | B11: =假設!$B$19*假設!$B$20 -> 49.032 | G11: ＝ RMB/EUR × NTD/RMB
A12: C1 固定費用：合規系統與團隊（NT$M/年） | B12: 25 | G12: 護照平台 €80–150k + EPR 27 國 + 團隊；假設
A13: C1 建置一次性（NT$M，第一年） | B13: 15 | G13: 系統與備品初始庫存
A14: C1 第一年出貨占穩態比例 | B14: 0.5 | G14: 爬坡
A16: C1 年出貨情境（台/年） | B16: 悲觀 | C16: 基準 | D16: 樂觀 | G16: 說明
A17: 三電白牌年出貨 | B17: 30000 | C17: 60000 | D17: 100000 | G17: 歐洲中價位用八方／安乃達的品牌約 30–45 萬台/年（估）
A18: 第 5 年在保台數 | B18: =B17*$B$10 -> 150000 | C18: =C17*$B$10 -> 300000 | D18: =D17*$B$10 -> 500000
A19: 第 5 年硬體毛利（NT$M） | B19: =B17*$B$6/(1-$B$7)*$B$7*$B$11/1000000 -> 26.9676 | C19: =C17*$B$6/(1-$B$7)*$B$7*$B$11/1000000 -> 53.9352 | D19: =D17*$B$6/(1-$B$7)*$B$7*$B$11/1000000 -> 89.892
A20: 第 5 年服務毛利（NT$M） | B20: =B18*($B$8-$B$9)*$B$11/1000000 -> 40.4514 | C20: =C18*($B$8-$B$9)*$B$11/1000000 -> 80.9028 | D20: =D18*($B$8-$B$9)*$B$11/1000000 -> 134.838
A21: 第 5 年營收（NT$M） | B21: =(B17*$B$6/(1-$B$7)+B18*$B$8)*$B$11/1000000 -> 181.4184 | C21: =(C17*$B$6/(1-$B$7)+C18*$B$8)*$B$11/1000000 -> 362.8368 | D21: =(D17*$B$6/(1-$B$7)+D18*$B$8)*$B$11/1000000 -> 604.728
A22: 第 5 年 EBIT（NT$M） | B22: =B19+B20-$B$12 -> 42.419 | C22: =C19+C20-$B$12 -> 109.838 | D22: =D19+D20-$B$12 -> 199.73
A23: 五年累計 EBIT（NT$M，服務基數線性累積） | B23: =5*B19+B20*(1+2+3+4+5)/5-5*$B$12-$B$13 -> 116.1922 | C23: =5*C19+C20*(1+2+3+4+5)/5-5*$B$12-$B$13 -> 372.3844 | D23: =5*D19+D20*(1+2+3+4+5)/5-5*$B$12-$B$13 -> 713.974
A24: 資金需求峰值（NT$M） | B24: =MAX($B$13+$B$12-(B19+B20/5)*$B$14,0) -> 22.47106 | C24: =MAX($B$13+$B$12-(C19+C20/5)*$B$14,0) -> 4.94212 | D24: =MAX($B$13+$B$12-(D19+D20/5)*$B$14,0) -> 0 | G24: 第一年：建置 + 固定費用 − 首年毛利；零電池資產、零 CAC
A26: B. B2C 情境（連動五年財務分頁，以量級倍數縮放）
A27: 項目 | B27: 悲觀 | C27: 基準 | D27: 樂觀 | G27: 說明
A28: 量級倍數（對五年財務基準 110k） | B28: 0.36 | C28: 1 | D28: 2.3 | G28: 悲觀 40k、基準 110k、樂觀 250k（SAM 4.7M 的 1–5%）
A29: 第 5 年出貨（台） | B29: =B28*五年財務!F6 -> 39600 | C29: =C28*五年財務!F6 -> 110000 | D29: =D28*五年財務!F6 -> 253000
A30: 第 5 年營收（NT$M） | B30: =B28*五年財務!F44 -> 449.41161 | C30: =C28*五年財務!F44 -> 1248.3656 | D30: =D28*五年財務!F44 -> 2871.2409
A31: 第 5 年 EBIT（NT$M） | B31: =B28*(五年財務!F45-五年財務!F48-五年財務!F49)-五年財務!F47 -> 43.379545 | C31: =C28*(五年財務!F45-五年財務!F48-五年財務!F49)-五年財務!F47 -> 159.60985 | D31: =D28*(五年財務!F45-五年財務!F48-五年財務!F49)-五年財務!F47 -> 395.70265 | G31: 毛利與變動費用隨量縮放，RD／APP／認證／翻新建置固定
A32: 五年累計現金流（NT$M） | B32: =B28*(五年財務!F54+SUM(五年財務!B47:F47))-SUM(五年財務!B47:F47) -> -72.235914 | C32: =C28*(五年財務!F54+SUM(五年財務!B47:F47))-SUM(五年財務!B47:F47) -> 0.2335724 | D32: =D28*(五年財務!F54+SUM(五年財務!B47:F47))-SUM(五年財務!B47:F47) -> 147.43722
A33: 資金需求峰值（NT$M，自持電池） | B33: =B28*(五年財務!B56-SUM(五年財務!B47:D47))+SUM(五年財務!B47:D47) -> 80.349826 | C33: =C28*(五年財務!B56-SUM(五年財務!B47:D47))+SUM(五年財務!B47:D47) -> 100.52729 | D33: =D28*(五年財務!B56-SUM(五年財務!B47:D47))+SUM(五年財務!B47:D47) -> 141.51278 | G33: 近似：峰值中的電池資本與 CAC 隨量縮放，前三年固定費用不縮放
A34: 資金需求峰值（NT$M，SPV 持有電池） | B34: =MAX(B28*(-五年財務!B57-SUM(五年財務!B47:C47))+SUM(五年財務!B47:C47),0) -> 35.343775 | C34: =MAX(C28*(-五年財務!B57-SUM(五年財務!B47:C47))+SUM(五年財務!B47:C47),0) -> 18.177152 | D34: =MAX(D28*(-五年財務!B57-SUM(五年財務!B47:C47))+SUM(五年財務!B47:C47),0) -> 0
A35: 第 5 年在訂戶（戶） | B35: =B28*五年財務!F36 -> 67955.501 | C35: =C28*五年財務!F36 -> 188765.28 | D35: =D28*五年財務!F36 -> 434160.14
A37: C. 五年對照（基準情境）
A38: 面向 | B38: C1 合規電池平台 + OEM 服務 | C38: B2C 低價整車 + 電池訂閱 | G38: 判讀
A39: 第 5 年營收（NT$M） | B39: =C21 -> 362.8368 | C39: =C30 -> 1248.3656 | G39: B2C 約為 C1 的 2.5–3 倍
A40: 第 5 年 EBIT（NT$M） | B40: =C22 -> 109.838 | C40: =C31 -> 159.60985 | G40: 同一數量級
A41: 資金需求峰值（NT$M） | B41: =C24 -> 4.94212 | C41: =C33 -> 100.52729 | G41: B2C 自持電池；SPV 時見 B 段
A42: EBIT ÷ 峰值資金（倍） | B42: =IF(C24>0,C22/C24,99) -> 22.224875 | C42: =C31/C33 -> 1.5877265 | G42: 資本效率
A43: 悲觀情境第 5 年 EBIT（NT$M） | B43: =B22 -> 42.419 | C43: =B31 -> 43.379545 | G43: 下檔
A44: 樂觀情境第 5 年 EBIT（NT$M） | B44: =D22 -> 199.73 | C44: =D31 -> 395.70265 | G44: 上檔
A45: 要新建的能力 | B45: 幾乎無：既有電池包業務延伸 | C45: C 端客服、催收、逆向物流、車隊管理、通路、品牌（2–3 年） | G45: V4 分頁 11
A46: 護城河 | B46: 車型級鎖定（認證 + 護照 + 備品），窗口 2027–2029 | C46: 電池池 + 資料迴圈（RMB 186/台級），營運型 | G46: 皆非技術型
A47: 最大單一風險 | B47: 合規被 BMZ／Bafang 歐洲實體／橫向 EPR 業者商品化；Omnibus 放寬 | C47: CAC 回到 €120 時單戶淨值趨近零 | G47: 見 D 段門檻
A48: 對手反應速度 | B48: 慢（需電池工程 + 法定生產者 + 通路） | C48: 快（硬體一週可複製；Giant／Decathlon 一季推 €499 級）
A49: 與 8/28 原則 | B49: 完全符合 | C49: 抵觸「不重資產」除非 SPV；毛利 15% 門檻第四年才過
A50: 右尾（第 5 年後） | B50: 小：受 OEM 家數與窗口限制 | C50: 大：訂閱裝機量複利，50 萬戶 ARR 約 NT$2B
A52: D. 決策門檻（B2C 放大前必須同時通過；藍字填入試點實測值）
A53: 門檻 | B53: 門檻值 | C53: 試點實測（填入） | D53: 判定 | G53: 說明
A54: CAC（€/戶，隨車或 B2B2C 通路） | B54: 40 | C54: 120 | D54: =IF(C54<=B54,"通過","未通過") -> 未通過 | G54: 薪資扣抵／法人通路才壓得到；B2C 電商 €120 不成立
A55: 12 個月訂閱留存 | B55: 0.8 | C55: 0 | D55: =IF(C55>=B55,"通過","未通過") -> 未通過 | G55: 2,000 台試點；低於 75% 單戶淨值轉薄
A56: 電池資產由 SPV 或租賃夥伴持有（1 = 是） | B56: 1 | C56: 0 | D56: =IF(C56>=B56,"通過","未通過") -> 未通過 | G56: 不重資產原則
A57: 種子車隊 duty cycle：日均 <15 km 占比 | B57: 0.6 | C57: 0 | D57: =IF(C57>=B57,"通過","未通過") -> 未通過 | G57: 支持 180／252／360Wh 分群，決定 RMB 117 槓桿
A58: 100k 量級 NT$6,000 隱含毛利（報價覆寫後） | B58: 0.08 | C58: 0.106 | D58: =IF(C58>=B58,"通過","未通過") -> 通過 | G58: 第一份模型 BOM 表 E40（台越廠 100k）；三檔書面報價後重算
A59: 綜合判定 | D59: =IF(COUNTIF(D54:D58,"通過")=5,"B2C 放大","B2C 停在 PB 通路 ODM 與 B2B 車隊；C1 為主業") -> B2C 停在 PB 通路 ODM 與 B2B 車隊；C1 為主業 | G59: 五項全過才放大；目前實測欄為預設值，須以試點數據覆寫
A61: E. C1 的三個終止訊號
A62: Omnibus VIII 定案後再延或放寬護照／可換性 → 2027 談判槓桿消失，服務費只剩 EPR 行政價
A63: BMZ 或 Bafang 歐洲實體在 2027 前推出「電池 + 護照 + 備品」套餐 → 整合空白被填掉
A64: 達方歐洲實體不承擔生產者的財務與法律責任 → 合規只能當代辦，鎖定效果減半
A66: F. TAM／SAM／SOM（B2C，台/年，估）
A67: 層級 | B67: 歐洲 | C67: 日本 | D67: 台灣 | E67: 合計 | G67: 依據
A68: 傳統（非電動）自行車年銷量 | B68: 8000000 | C68: 4000000 | D68: 400000 | E68: =SUM(B68:D68) -> 12400000 | G68: 歐洲總量 12–13M 扣 e-bike 4.5–5M；日本由電助力 78 萬台占 16% 反推；台灣無統計
A69: 都會通勤、€400–800／¥25–45k 價格帶（SAM） | B69: 2500000 | C69: 2000000 | D69: 200000 | E69: =SUM(B69:D69) -> 4700000 | G69: 估：約三至五成
A70: 五年可取得 2%（SOM 低） | B70: =B69*0.02 -> 50000 | C70: =C69*0.02 -> 40000 | D70: =D69*0.02 -> 4000 | E70: =SUM(B70:D70) -> 94000 | G70: ＝ SAM × 2%
A71: 五年可取得 5%（SOM 高） | B71: =B69*0.05 -> 125000 | C71: =C69*0.05 -> 100000 | D71: =D69*0.05 -> 10000 | E71: =SUM(B71:D71) -> 235000 | G71: ＝ SAM × 5%
A72: SAM 金額（車體 + 首年訂閱，NT$M） | B72: =B69*(入手價!B17+電池訂閱費!C19*12)*$B$11/1000000 -> 37148.739 | C72: =C69*(入手價!B30+電池訂閱費!C61*12)/假設!$B$21*假設!$B$20/1000000 -> 24738.601 | D72: =D69*(入手價!C17+電池訂閱費!C40*12)/1000000 -> 2150.5838 | E72: =SUM(B72:D72) -> 64037.924 | G72: 逆向打擊傳統車只在歐洲成立（入手價 < 一般自行車均價）；日本打的是電助力車
